retort/__init__.py
retort/app.py
retort/cache.py
retort/cookie.py
retort/data.py
retort/exceptions.py
retort/response.py
retort/route.py
retort/session.py
retort_cgi-1.0.1.dist-info/METADATA
retort_cgi-1.0.1.dist-info/RECORD
retort_cgi-1.0.1.dist-info/WHEEL
retort_cgi-1.0.1.dist-info/top_level.txt
