Metadata-Version: 2.1
Name: retort-cgi
Version: 1.0.1
Summary: Lightweight Python CGI framework.
Home-page: https://github.com/kynikos/retort
Author: Dario Giovannetti
Author-email: dev@dariogiovannetti.net
License: GPLv3+
Keywords: html web development
Platform: UNKNOWN
Classifier: Development Status :: 4 - Beta
Classifier: Environment :: Web Environment
Classifier: Intended Audience :: Developers
Classifier: Topic :: Internet :: WWW/HTTP :: Dynamic Content :: CGI Tools/Libraries
Classifier: License :: OSI Approved :: GNU General Public License v3 or later (GPLv3+)
Classifier: Programming Language :: Python :: 2
Classifier: Programming Language :: Python :: 2.6
Classifier: Programming Language :: Python :: 2.7
Classifier: Programming Language :: Python :: 3
Classifier: Programming Language :: Python :: 3.6
Classifier: Programming Language :: Python :: 3.7
